gridfm_graphkit/__init__.py
gridfm_graphkit/__main__.py
gridfm_graphkit/cli.py
gridfm_graphkit/datasets/__init__.py
gridfm_graphkit/datasets/globals.py
gridfm_graphkit/datasets/normalizers.py
gridfm_graphkit/datasets/postprocessing.py
gridfm_graphkit/datasets/powergrid_datamodule.py
gridfm_graphkit/datasets/powergrid_dataset.py
gridfm_graphkit/datasets/transforms.py
gridfm_graphkit/datasets/utils.py
gridfm_graphkit/io/__init__.py
gridfm_graphkit/io/param_handler.py
gridfm_graphkit/io/registries.py
gridfm_graphkit/models/__init__.py
gridfm_graphkit/models/gnn_transformer.py
gridfm_graphkit/models/gps_transformer.py
gridfm_graphkit/tasks/__init__.py
gridfm_graphkit/tasks/feature_reconstruction_task.py
gridfm_graphkit/training/__init__.py
gridfm_graphkit/training/callbacks.py
gridfm_graphkit/training/loss.py
gridfm_graphkit/utils/__init__.py
gridfm_graphkit/utils/utils.py
gridfm_graphkit/utils/visualization.py
gridfm_graphkit-0.0.6.dist-info/licenses/LICENSE
gridfm_graphkit-0.0.6.dist-info/METADATA
gridfm_graphkit-0.0.6.dist-info/WHEEL
gridfm_graphkit-0.0.6.dist-info/entry_points.txt
gridfm_graphkit-0.0.6.dist-info/top_level.txt
gridfm_graphkit-0.0.6.dist-info/RECORD
