Metadata-Version: 2.4
Name: gridfm-graphkit
Version: 0.0.6
Summary: Grid Foundation Model
Author-email: Matteo Mazzonelli <matteo.mazzonelli1@ibm.com>, Alban Puech <apuech@seas.harvard.edu>, Tamara Govindasamy <tamara.govindasamy@ibm.com>, Mangaliso Mngomezulu <mngomezulum@ibm.com>, Etienne Vos <etienne.vos@ibm.com>, Celia Cintas <celia.cintas@ibm.com>, Jonas Weiss <jwe@zurich.ibm.com>
Maintainer-email: Matteo Mazzonelli <matteo.mazzonelli1@ibm.com>
License-Expression: Apache-2.0
Keywords: electric power grid,foundational model,graph neural networks
Classifier: Development Status :: 2 - Pre-Alpha
Classifier: Programming Language :: Python :: 3.10
Classifier: Programming Language :: Python :: 3.11
Classifier: Programming Language :: Python :: 3.12
Classifier: Topic :: Scientific/Engineering :: Artificial Intelligence
Requires-Python: <3.13,>=3.10
License-File: LICENSE
Requires-Dist: torch>2.0
Requires-Dist: torch-geometric
Requires-Dist: mlflow
Requires-Dist: nbformat
Requires-Dist: networkx
Requires-Dist: numpy
Requires-Dist: pandas
Requires-Dist: plotly
Requires-Dist: pyyaml
Requires-Dist: lightning
Requires-Dist: seaborn
Provides-Extra: dev
Requires-Dist: mkdocs-material; extra == "dev"
Requires-Dist: mkdocstrings[python]; extra == "dev"
Requires-Dist: pre-commit; extra == "dev"
Requires-Dist: bandit; extra == "dev"
Requires-Dist: build; extra == "dev"
Provides-Extra: test
Requires-Dist: pytest; extra == "test"
Requires-Dist: pytest-cov; extra == "test"
Dynamic: license-file
